{"themes": [{"name": "blackboard", "colors": {"accent": "#5c5c5c", "primary": "#FFFDEA", "background": "#1a1a1a"}, "isCustom": false}, {"name": "gazette", "colors": {"accent": "#5c5c5c", "primary": "#000000", "background": "#F2F7FF"}, "isCustom": false}, {"name": "espresso", "colors": {"accent": "#4E4E4E", "primary": "#D1B59A", "background": "#21211F"}, "isCustom": false}, {"name": "cab", "colors": {"accent": "#424242", "primary": "#1F1F1F", "background": "#F6D305"}, "isCustom": false}, {"name": "cloud", "colors": {"accent": "#37bbe4", "primary": "#35342f", "background": "#f1f2f0"}, "isCustom": false}, {"name": "lime", "colors": {"accent": "#aeea00", "primary": "#AABBC3", "background": "#263238"}, "isCustom": false}, {"name": "white", "colors": {"accent": "#dddddd", "primary": "#222222", "background": "#ffffff"}, "isCustom": false}, {"name": "tron", "colors": {"accent": "#6EE2FF", "primary": "#EFFBFF", "background": "#242B33"}, "isCustom": false}, {"name": "blues", "colors": {"accent": "#6677EB", "primary": "#EFF1FC", "background": "#2B2C56"}, "isCustom": false}, {"name": "passion", "colors": {"accent": "#8e24aa", "primary": "#12005e", "background": "#f5f5f5"}, "isCustom": false}, {"name": "chalk", "colors": {"accent": "#FF869A", "primary": "#AABBC3", "background": "#263238"}, "isCustom": false}, {"name": "paper", "colors": {"accent": "#AA9A73", "primary": "#4C432E", "background": "#F8F6F1"}, "isCustom": false}, {"name": "neon", "colors": {"accent": "#ea00d9", "primary": "#EFFBFF", "background": "#091833"}, "isCustom": false}, {"name": "pumpkin", "colors": {"accent": "#ffa500", "primary": "#EFFBFF", "background": "#2d3436"}, "isCustom": false}, {"name": "onedark", "colors": {"accent": "#98c379", "primary": "#dfd9d6", "background": "#282c34"}, "isCustom": false}, {"name": "mint", "colors": {"accent": "#50fbc2", "primary": "#d9d9d9", "background": "#282525"}, "isCustom": false}, {"name": "Horowod", "colors": {"accent": "#98c379", "primary": "#dfd9d6", "background": "#004c2c"}, "isCustom": true}]}
